peal/__init__.py
peal-0.1.0.dist-info/LICENSE
peal-0.1.0.dist-info/WHEEL
peal-0.1.0.dist-info/METADATA
peal-0.1.0.dist-info/RECORD
